ase_grain/__init__.py
ase_grain/_version.py
ase_grain/base.py
ase_grain/monkey_patch.py
ase_grain/tasks.py
ase_grain/util.py
ase_grain/tests/__init__.py
ase_grain/tests/test_tasks.py
ase_grain-0.1.4.dist-info/METADATA
ase_grain-0.1.4.dist-info/WHEEL
ase_grain-0.1.4.dist-info/top_level.txt
ase_grain-0.1.4.dist-info/RECORD
