Metadata-Version: 2.1
Name: ase-grain
Version: 0.1.4
Summary: An async wrapper for ASE
Home-page: https://github.com/Contextualist/ase-grain
Author: Harry Zhang
Author-email: zhanghar@iu.edu
License: UNKNOWN
Platform: UNKNOWN
Classifier: Development Status :: 2 - Pre-Alpha
Classifier: Programming Language :: Python :: 3 :: Only
Classifier: Programming Language :: Python :: 3.6
Classifier: Programming Language :: Python :: 3.7
Classifier: Programming Language :: Python :: 3.8
Classifier: Programming Language :: Python :: 3.9
Classifier: Programming Language :: Python :: 3.10
Classifier: Framework :: Trio
Classifier: Intended Audience :: Science/Research
Classifier: Topic :: Scientific/Engineering
Requires-Python: >=3.6
Requires-Dist: ase (<3.23.0,>=3.22.0)
Requires-Dist: grain-scheduler (>=0.12.1)
Requires-Dist: trio
